markovconstraints/__init__.py
markovconstraints/markov_automata.py
markovconstraints/markov_chain.py
markovconstraints/suffix_tree.py
markovconstraints/tests/__init__.py
markovconstraints/tests/test_markov.py
markovconstraints-0.1.dist-info/LICENSE
markovconstraints-0.1.dist-info/METADATA
markovconstraints-0.1.dist-info/WHEEL
markovconstraints-0.1.dist-info/top_level.txt
markovconstraints-0.1.dist-info/RECORD
