Metadata-Version: 2.1
Name: markovconstraints
Version: 0.1
Summary: A Markov constraint satisfaction problem solver
Home-page: https://github.com/gabrielebarbieri/markovconstraints
Author: Gabriele Barbieri
Author-email: gabriele.barbieri83@gmail.com
License: MIT
Platform: UNKNOWN
Classifier: Programming Language :: Python :: 3
Classifier: License :: OSI Approved :: MIT License
Classifier: Operating System :: OS Independent
Requires-Python: >=3.6
Requires-Dist: numpy
Requires-Dist: pandas
